Metadata-Version: 1.0
Name: kangeioracle
Version: 0.1.2
Summary: Youkoso module
Home-page: https://github.com/miorgash/kangeioracle
Author: Miori Igarashi
Author-email: miorgash@gmail.com
License: MIT License
